Metadata-Version: 2.4
Name: prompt_poet
Version: 0.0.50
Summary: Streamlines and simplifies prompt design for both developers and non-technical users with a low code approach.
Home-page: https://github.com/character-ai/prompt-poet
Author: James Groeneveld
Author-email: james@character.ai
License: MIT
Requires-Python: >=3.10
License-File: LICENSE
Requires-Dist: jinja2>=3.0.0
Requires-Dist: PyYaml>=6.0.0
Requires-Dist: cachetools==5.3.3
Requires-Dist: tiktoken==0.7.0
Requires-Dist: google-cloud-storage==2.19.0
Dynamic: author
Dynamic: author-email
Dynamic: description
Dynamic: description-content-type
Dynamic: home-page
Dynamic: license
Dynamic: license-file
Dynamic: requires-dist
Dynamic: requires-python
Dynamic: summary
